.gitignore
LICENSE.txt
README.rst
bootstrap.py
buildout.cfg
setup.py
motmot/__init__.py
motmot.flytrax.egg-info/.gitignore
motmot.flytrax.egg-info/PKG-INFO
motmot.flytrax.egg-info/SOURCES.txt
motmot.flytrax.egg-info/dependency_links.txt
motmot.flytrax.egg-info/entry_points.txt
motmot.flytrax.egg-info/namespace_packages.txt
motmot.flytrax.egg-info/not-zip-safe
motmot.flytrax.egg-info/requires.txt
motmot.flytrax.egg-info/stdeb.cfg
motmot.flytrax.egg-info/top_level.txt
motmot/flytrax/__init__.py
motmot/flytrax/flytrax.py
motmot/flytrax/flytrax.xrc
motmot/flytrax/generate_fake_trx_file.py
motmot/flytrax/read_trx.m
motmot/flytrax/strip_blank_xrc_lines.py
motmot/flytrax/tests.py
motmot/flytrax/trax_replay.py
motmot/flytrax/trax_replay.xrc
motmot/flytrax/trax_udp_sender.py
motmot/flytrax/trax_udp_sender.xrc
motmot/flytrax/traxio.py
motmot/flytrax/trx2fullframefmf.py