Metadata-Version: 1.0
Name: motmot.flytrax
Version: 0.5.8
Summary: plugin for fview to perform 2D image tracking (part of the motmot camera packages)
Home-page: http://code.astraw.com/projects/motmot
Author: Andrew Straw
Author-email: strawman@astraw.com
License: BSD
Platform: UNKNOWN
